{
  "name": "azure",
  "title": "Azure Sphere",
  "description": "Azure Sphere Development PlatformIO 2019 Georgi Angelov",
  "url": "https://github.com/Wiz-IO",
  "homepage": "http://www.wizio.eu/",
  "license": "Apache-2.0",
  "engines": { "platformio": "^3.0.0" },
  "repository": {
    "type": "git",
    "url": "https://github.com/Wiz-IO/platform-azure.git"
  },
  "version": "1.0.0",
  "packageRepositories": [
    "https://dl.bintray.com/platformio/dl-packages/manifest.json",
    "http://dl.platformio.org/packages/manifest.json"
  ],
  "frameworks": {
      "arduino": {
        "package": "framework-azure",
        "script": "builder/frameworks/arduino.py"
      },   
      "linux": {
        "package": "framework-azure",
        "script": "builder/frameworks/linux.py"
      },     
      "baremetal": {
        "package": "framework-azure",
        "script": "builder/frameworks/baremetal.py"
      },
      "wiring": {
        "package": "framework-azure",
        "script": "builder/frameworks/wiring.py"
      }      
  },
  "packages": {
    "framework-azure": {
        "type": "framework",
        "version": "https://github.com/Wiz-IO/framework-azure.git"
    },
    "toolchain-arm-poky-linux-musleabi-hf": {
      "type": "toolchain",
      "version": "http://wizio.eu/azure/toolchain-arm-poky-linux-musleabi-hf-1.0.0.zip"
    },
    "toolchain-gccarmnoneeabi": {
      "type": "toolchain",
      "version": "=1.70201.0"
    },    
    "tool-azure": {
      "type": "uploader",
      "version": "https://github.com/Wiz-IO/tool-azure.git"
    }        
  }
}
